muninflux
setup.py
munin_influxdb.egg-info/PKG-INFO
munin_influxdb.egg-info/SOURCES.txt
munin_influxdb.egg-info/dependency_links.txt
munin_influxdb.egg-info/requires.txt
munin_influxdb.egg-info/top_level.txt
munininfluxdb/__init__.py
munininfluxdb/grafana.py
munininfluxdb/influxdbclient.py
munininfluxdb/munin.py
munininfluxdb/rfetch.py
munininfluxdb/rrd.py
munininfluxdb/settings.py
munininfluxdb/utils.py
vendor/__init__.py
vendor/crontab.py
vendor/storable.py