Metadata-Version: 1.1
Name: munin-influxdb
Version: 1.2.2
Summary: Munin to InfluxDB/Grafana gateway
Home-page: http://github.com/mvonthron/munin-influxdb
Author: Manuel Vonthron
Author-email: manuel.vonthron@acadis.org
License: BSD
Platform: UNKNOWN
Classifier: Development Status :: 4 - Beta
Classifier: Environment :: Console
Classifier: Intended Audience :: Developers
Classifier: Intended Audience :: Information Technology
Classifier: License :: OSI Approved :: BSD License
Classifier: Programming Language :: Python
Classifier: Topic :: System :: Monitoring
